[{"category_id":"999989","category_name":"TOP POPULARES","parent_id":0},{"category_id":"61095","category_name":"FIV | LANÇAMENTOS LEGENDADOS","parent_id":0},{"category_id":"61108","category_name":"FIV | LANCAMENTOS","parent_id":0},{"category_id":"443","category_name":"ELT | LANCAMENTOS","parent_id":0},{"category_id":"233","category_name":"CLB | Lancamentos","parent_id":0},{"category_id":"23982","category_name":"CLB | Oscar 2024","parent_id":0},{"category_id":"2304","category_name":"CLB | Legendados","parent_id":0},{"category_id":"2299","category_name":"CLB | 4K","parent_id":0},{"category_id":"2317","category_name":"CLB | Cinema","parent_id":0},{"category_id":"223","category_name":"CLB | Acao","parent_id":0},{"category_id":"222","category_name":"CLB | Animacao","parent_id":0},{"category_id":"23483","category_name":"CLB | Aventura","parent_id":0},{"category_id":"225","category_name":"CLB | Comedia","parent_id":0},{"category_id":"23487","category_name":"CLB | Crime","parent_id":0},{"category_id":"226","category_name":"CLB | Drama","parent_id":0},{"category_id":"23494","category_name":"CLB | Família","parent_id":0},{"category_id":"228","category_name":"CLB | Fantasia","parent_id":0},{"category_id":"229","category_name":"CLB | Faroeste","parent_id":0},{"category_id":"21798","category_name":"CLB | Ficcao","parent_id":0},{"category_id":"23542","category_name":"CLB | Guerra","parent_id":0},{"category_id":"232","category_name":"CLB | Infantis","parent_id":0},{"category_id":"2303","category_name":"CLB | Nacionais","parent_id":0},{"category_id":"236","category_name":"CLB | Religiosos","parent_id":0},{"category_id":"237","category_name":"CLB | Romance","parent_id":0},{"category_id":"238","category_name":"CLB | Suspense","parent_id":0},{"category_id":"239","category_name":"CLB | Terror","parent_id":0},{"category_id":"23961","category_name":"CLB | Dublagem Nao Oficial","parent_id":0},{"category_id":"2302","category_name":"CLB | Documentarios","parent_id":0},{"category_id":"241","category_name":"CLB | Shows","parent_id":0},{"category_id":"2611","category_name":"CLB | Stand Up Comedy","parent_id":0},{"category_id":"23983","category_name":"CLB | nacional","parent_id":0},{"category_id":"4652","category_name":"ELT | 4K FILMES","parent_id":0},{"category_id":"425","category_name":"ELT | ACAO","parent_id":0},{"category_id":"426","category_name":"ELT | ANIMACAO & INFANTIL","parent_id":0},{"category_id":"427","category_name":"ELT | ANIMES E LIVE-ACTIONS","parent_id":0},{"category_id":"428","category_name":"ELT | AVENTURA","parent_id":0},{"category_id":"430","category_name":"ELT | CLASSICOS","parent_id":0},{"category_id":"4156","category_name":"ELT | BIOGRAFIAS","parent_id":0},{"category_id":"431","category_name":"ELT | COMEDIA","parent_id":0},{"category_id":"432","category_name":"ELT | CRIME","parent_id":0},{"category_id":"433","category_name":"ELT | DOCUMENTARIO","parent_id":0},{"category_id":"434","category_name":"ELT | DRAMA","parent_id":0},{"category_id":"435","category_name":"ELT | EVANGELICOS","parent_id":0},{"category_id":"437","category_name":"ELT | FANTASIA","parent_id":0},{"category_id":"436","category_name":"ELT | FAMILIA","parent_id":0},{"category_id":"438","category_name":"ELT | FAROESTE","parent_id":0},{"category_id":"439","category_name":"ELT | FICCAO CIENTIFICA","parent_id":0},{"category_id":"494","category_name":"ELT | MARVEL","parent_id":0},{"category_id":"441","category_name":"ELT | HISTORIA","parent_id":0},{"category_id":"444","category_name":"ELT | MISTERIO","parent_id":0},{"category_id":"4130","category_name":"ELT | SHOWS E DVS MUSICAIS","parent_id":0},{"category_id":"445","category_name":"ELT | MUSICA","parent_id":0},{"category_id":"446","category_name":"ELT | NACIONAIS","parent_id":0},{"category_id":"447","category_name":"ELT | ROMANCE","parent_id":0},{"category_id":"448","category_name":"ELT | SUSPENSE","parent_id":0},{"category_id":"449","category_name":"ELT | TERROR","parent_id":0},{"category_id":"610002","category_name":"FIV | INDICADOS AO OSCAR 2024","parent_id":0},{"category_id":"6174","category_name":"FIV | CINEMA","parent_id":0},{"category_id":"61093","category_name":"FIV | STAND-UP","parent_id":0},{"category_id":"6411","category_name":"FIV | UHD 4K","parent_id":0},{"category_id":"620","category_name":"FIV | ACAO","parent_id":0},{"category_id":"627","category_name":"FIV | ANIMACAO/INFANTIL","parent_id":0},{"category_id":"6700","category_name":"FIV | ANIMES","parent_id":0},{"category_id":"625","category_name":"FIV | COMEDIA","parent_id":0},{"category_id":"618","category_name":"FIV | DRAMA","parent_id":0},{"category_id":"6324","category_name":"FIV | DOCUMENTARIOS","parent_id":0},{"category_id":"6149","category_name":"FIV | DC","parent_id":0},{"category_id":"61079","category_name":"FIV | ESPECIAL DE NATAL","parent_id":0},{"category_id":"621","category_name":"FIV | FAROESTE","parent_id":0},{"category_id":"648","category_name":"FIV | FICCAO/FANTASIA","parent_id":0},{"category_id":"647","category_name":"FIV | GUERRA","parent_id":0},{"category_id":"6148","category_name":"FIV | MARVEL","parent_id":0},{"category_id":"622","category_name":"FIV | NACIONAIS","parent_id":0},{"category_id":"624","category_name":"FIV | TERROR","parent_id":0},{"category_id":"626","category_name":"FIV | ROMANCE","parent_id":0},{"category_id":"628","category_name":"FIV | RELIGIOSOS","parent_id":0},{"category_id":"619","category_name":"FIV | SUSPENSE","parent_id":0},{"category_id":"6615","category_name":"FIV | LEGENDADOS","parent_id":0},{"category_id":"6232","category_name":"FIV | SHOWS NACIONAIS","parent_id":0},{"category_id":"6231","category_name":"FIV | SHOWS INTERNACIONAIS","parent_id":0}]